{"nodes": [{"id": "13", "group": 0}, {"id": "14", "group": 0}, {"id": "95", "group": 0}, {"id": "96", "group": 0}, {"id": "97", "group": 0}, {"id": "98", "group": 0}, {"id": "99", "group": 0}, {"id": "100", "group": 0}, {"id": "105", "group": 0}, {"id": "106", "group": 0}, {"id": "107", "group": 0}, {"id": "108", "group": 0}, {"id": "109", "group": 0}, {"id": "110", "group": 0}, {"id": "111", "group": 0}, {"id": "112", "group": 0}, {"id": "113", "group": 0}, {"id": "114", "group": 0}, {"id": "115", "group": 0}, {"id": "116", "group": 0}, {"id": "117", "group": 0}, {"id": "118", "group": 0}, {"id": "119", "group": 0}, {"id": "122", "group": 0}, {"id": "123", "group": 0}, {"id": "124", "group": 0}, {"id": "125", "group": 0}, {"id": "126", "group": 0}, {"id": "127", "group": 0}, {"id": "128", "group": 0}, {"id": "129", "group": 0}, {"id": "130", "group": 0}, {"id": "131", "group": 0}, {"id": "132", "group": 0}, {"id": "133", "group": 0}, {"id": "134", "group": 0}, {"id": "135", "group": 0}, {"id": "136", "group": 0}, {"id": "165", "group": 0}, {"id": "166", "group": 0}, {"id": "169", "group": 0}, {"id": "170", "group": 0}, {"id": "171", "group": 0}, {"id": "172", "group": 0}, {"id": "173", "group": 0}, {"id": "174", "group": 0}, {"id": "175", "group": 0}, {"id": "176", "group": 0}, {"id": "177", "group": 0}, {"id": "178", "group": 0}, {"id": "179", "group": 0}, {"id": "180", "group": 0}, {"id": "181", "group": 0}, {"id": "182", "group": 0}, {"id": "183", "group": 0}, {"id": "184", "group": 0}, {"id": "185", "group": 0}, {"id": "186", "group": 0}, {"id": "187", "group": 0}, {"id": "188", "group": 0}, {"id": "189", "group": 0}, {"id": "190", "group": 0}, {"id": "191", "group": 0}, {"id": "192", "group": 0}, {"id": "193", "group": 0}, {"id": "194", "group": 0}, {"id": "195", "group": 0}, {"id": "196", "group": 0}, {"id": "197", "group": 0}, {"id": "198", "group": 0}, {"id": "199", "group": 0}, {"id": "200", "group": 0}, {"id": "201", "group": 0}, {"id": "202", "group": 0}, {"id": "203", "group": 0}, {"id": "204", "group": 0}, {"id": "205", "group": 0}, {"id": "206", "group": 0}, {"id": "207", "group": 0}, {"id": "208", "group": 0}, {"id": "209", "group": 0}, {"id": "210", "group": 0}, {"id": "211", "group": 0}, {"id": "212", "group": 0}, {"id": "213", "group": 0}, {"id": "214", "group": 0}, {"id": "215", "group": 0}, {"id": "216", "group": 0}, {"id": "217", "group": 0}, {"id": "218", "group": 0}, {"id": "219", "group": 0}, {"id": "220", "group": 0}, {"id": "221", "group": 0}, {"id": "222", "group": 0}, {"id": "223", "group": 0}, {"id": "224", "group": 0}, {"id": "225", "group": 0}, {"id": "226", "group": 0}, {"id": "227", "group": 0}, {"id": "228", "group": 0}, {"id": "230", "group": 0}, {"id": "231", "group": 0}, {"id": "232", "group": 0}, {"id": "233", "group": 0}, {"id": "234", "group": 0}, {"id": "235", "group": 0}, {"id": "236", "group": 0}, {"id": "237", "group": 0}, {"id": "238", "group": 0}, {"id": "239", "group": 0}, {"id": "240", "group": 0}, {"id": "241", "group": 0}, {"id": "242", "group": 0}, {"id": "243", "group": 0}, {"id": "244", "group": 0}, {"id": "245", "group": 0}, {"id": "246", "group": 0}, {"id": "247", "group": 0}, {"id": "249", "group": 0}, {"id": "250", "group": 0}, {"id": "251", "group": 0}, {"id": "252", "group": 0}, {"id": "253", "group": 0}, {"id": "254", "group": 0}, {"id": "255", "group": 0}, {"id": "256", "group": 0}, {"id": "257", "group": 0}, {"id": "258", "group": 0}, {"id": "259", "group": 0}, {"id": "260", "group": 0}, {"id": "261", "group": 0}, {"id": "262", "group": 0}, {"id": "263", "group": 0}, {"id": "264", "group": 0}, {"id": "265", "group": 0}, {"id": "266", "group": 0}, {"id": "267", "group": 0}, {"id": "268", "group": 0}, {"id": "269", "group": 0}, {"id": "270", "group": 0}, {"id": "271", "group": 0}, {"id": "272", "group": 0}, {"id": "273", "group": 0}, {"id": "274", "group": 0}, {"id": "275", "group": 0}, {"id": "276", "group": 0}, {"id": "277", "group": 0}, {"id": "278", "group": 0}, {"id": "279", "group": 0}, {"id": "280", "group": 0}, {"id": "281", "group": 0}, {"id": "282", "group": 0}, {"id": "283", "group": 0}, {"id": "284", "group": 0}, {"id": "285", "group": 0}, {"id": "286", "group": 0}, {"id": "287", "group": 0}, {"id": "288", "group": 0}, {"id": "289", "group": 0}, {"id": "290", "group": 0}, {"id": "291", "group": 0}, {"id": "292", "group": 0}, {"id": "293", "group": 0}, {"id": "294", "group": 0}, {"id": "295", "group": 0}, {"id": "296", "group": 0}, {"id": "297", "group": 0}, {"id": "298", "group": 0}, {"id": "299", "group": 0}, {"id": "300", "group": 0}], "links": [{"source": "13", "target": "14", "value": 1.71375}, {"source": "14", "target": "13", "value": 1.71375}, {"source": "95", "target": "96", "value": 2.93125}, {"source": "96", "target": "95", "value": 2.93125}, {"source": "97", "target": "98", "value": 3.87625}, {"source": "98", "target": "97", "value": 3.87625}, {"source": "99", "target": "100", "value": 3.97125}, {"source": "100", "target": "99", "value": 3.97125}, {"source": "105", "target": "106", "value": 7.23875}, {"source": "106", "target": "105", "value": 7.23875}, {"source": "107", "target": "108", "value": 2.85625}, {"source": "108", "target": "107", "value": 2.85625}, {"source": "109", "target": "108", "value": 5.99875}, {"source": "108", "target": "109", "value": 5.99875}, {"source": "108", "target": "105", "value": 4.62625}, {"source": "105", "target": "108", "value": 4.62625}, {"source": "110", "target": "105", "value": 1.15125}, {"source": "105", "target": "110", "value": 1.15125}, {"source": "111", "target": "109", "value": 3.7525}, {"source": "109", "target": "111", "value": 3.7525}, {"source": "112", "target": "113", "value": 0.13875}, {"source": "113", "target": "112", "value": 0.13875}, {"source": "114", "target": "112", "value": 1.795}, {"source": "112", "target": "114", "value": 1.795}, {"source": "115", "target": "116", "value": 5.3}, {"source": "116", "target": "115", "value": 5.3}, {"source": "117", "target": "118", "value": 1.315}, {"source": "118", "target": "117", "value": 1.315}, {"source": "117", "target": "115", "value": 3.18875}, {"source": "115", "target": "117", "value": 3.18875}, {"source": "119", "target": "117", "value": 4.53875}, {"source": "117", "target": "119", "value": 4.53875}, {"source": "122", "target": "119", "value": 1.93375}, {"source": "119", "target": "122", "value": 1.93375}, {"source": "122", "target": "123", "value": 2.6725}, {"source": "123", "target": "122", "value": 2.6725}, {"source": "124", "target": "122", "value": 4.4925}, {"source": "122", "target": "124", "value": 4.4925}, {"source": "125", "target": "126", "value": 1.28875}, {"source": "126", "target": "125", "value": 1.28875}, {"source": "125", "target": "127", "value": 2.60625}, {"source": "127", "target": "125", "value": 2.60625}, {"source": "124", "target": "125", "value": 2.7075}, {"source": "125", "target": "124", "value": 2.7075}, {"source": "128", "target": "124", "value": 0.655}, {"source": "124", "target": "128", "value": 0.655}, {"source": "129", "target": "128", "value": 8.69875}, {"source": "128", "target": "129", "value": 8.69875}, {"source": "129", "target": "130", "value": 6.86875}, {"source": "130", "target": "129", "value": 6.86875}, {"source": "130", "target": "131", "value": 1.57625}, {"source": "131", "target": "130", "value": 1.57625}, {"source": "132", "target": "133", "value": 3.6075}, {"source": "133", "target": "132", "value": 3.6075}, {"source": "130", "target": "133", "value": 5.3075}, {"source": "133", "target": "130", "value": 5.3075}, {"source": "134", "target": "135", "value": 0.66875}, {"source": "135", "target": "134", "value": 0.66875}, {"source": "133", "target": "134", "value": 1.25625}, {"source": "134", "target": "133", "value": 1.25625}, {"source": "134", "target": "136", "value": 2.1075}, {"source": "136", "target": "134", "value": 2.1075}, {"source": "165", "target": "166", "value": 4.91375}, {"source": "166", "target": "165", "value": 4.91375}, {"source": "169", "target": "165", "value": 3.25625}, {"source": "165", "target": "169", "value": 3.25625}, {"source": "170", "target": "165", "value": 1.155}, {"source": "165", "target": "170", "value": 1.155}, {"source": "170", "target": "171", "value": 4.26875}, {"source": "171", "target": "170", "value": 4.26875}, {"source": "172", "target": "173", "value": 2.45375}, {"source": "173", "target": "172", "value": 2.45375}, {"source": "111", "target": "174", "value": 7.77875}, {"source": "174", "target": "111", "value": 7.77875}, {"source": "166", "target": "111", "value": 6.015}, {"source": "111", "target": "166", "value": 6.015}, {"source": "174", "target": "166", "value": 3.4425}, {"source": "166", "target": "174", "value": 3.4425}, {"source": "175", "target": "174", "value": 5.99375}, {"source": "174", "target": "175", "value": 5.99375}, {"source": "171", "target": "176", "value": 4.68}, {"source": "176", "target": "171", "value": 4.68}, {"source": "177", "target": "170", "value": 10.12125}, {"source": "170", "target": "177", "value": 10.12125}, {"source": "178", "target": "179", "value": 1.1475}, {"source": "179", "target": "178", "value": 1.1475}, {"source": "180", "target": "172", "value": 2.28625}, {"source": "172", "target": "180", "value": 2.28625}, {"source": "181", "target": "180", "value": 0.7025}, {"source": "180", "target": "181", "value": 0.7025}, {"source": "181", "target": "182", "value": 2.6525}, {"source": "182", "target": "181", "value": 2.6525}, {"source": "183", "target": "181", "value": 6.20125}, {"source": "181", "target": "183", "value": 6.20125}, {"source": "182", "target": "184", "value": 1.11125}, {"source": "184", "target": "182", "value": 1.11125}, {"source": "172", "target": "178", "value": 5.3525}, {"source": "178", "target": "172", "value": 5.3525}, {"source": "178", "target": "185", "value": 4.81375}, {"source": "185", "target": "178", "value": 4.81375}, {"source": "175", "target": "186", "value": 6.94875}, {"source": "186", "target": "175", "value": 6.94875}, {"source": "187", "target": "188", "value": 1.12625}, {"source": "188", "target": "187", "value": 1.12625}, {"source": "187", "target": "189", "value": 0.9775}, {"source": "189", "target": "187", "value": 0.9775}, {"source": "190", "target": "191", "value": 4.91625}, {"source": "191", "target": "190", "value": 4.91625}, {"source": "190", "target": "175", "value": 1.5075}, {"source": "175", "target": "190", "value": 1.5075}, {"source": "192", "target": "190", "value": 3.36875}, {"source": "190", "target": "192", "value": 3.36875}, {"source": "193", "target": "192", "value": 0.63875}, {"source": "192", "target": "193", "value": 0.63875}, {"source": "194", "target": "193", "value": 0.87}, {"source": "193", "target": "194", "value": 0.87}, {"source": "195", "target": "196", "value": 4.0975}, {"source": "196", "target": "195", "value": 4.0975}, {"source": "197", "target": "194", "value": 2.065}, {"source": "194", "target": "197", "value": 2.065}, {"source": "194", "target": "198", "value": 7.04375}, {"source": "198", "target": "194", "value": 7.04375}, {"source": "192", "target": "199", "value": 3.7575}, {"source": "199", "target": "192", "value": 3.7575}, {"source": "199", "target": "200", "value": 0.49125}, {"source": "200", "target": "199", "value": 0.49125}, {"source": "180", "target": "201", "value": 10.68}, {"source": "201", "target": "180", "value": 10.68}, {"source": "202", "target": "203", "value": 9.64}, {"source": "203", "target": "202", "value": 9.64}, {"source": "201", "target": "195", "value": 11.04}, {"source": "195", "target": "201", "value": 11.04}, {"source": "204", "target": "195", "value": 2.1825}, {"source": "195", "target": "204", "value": 2.1825}, {"source": "204", "target": "205", "value": 2.81125}, {"source": "205", "target": "204", "value": 2.81125}, {"source": "206", "target": "202", "value": 8.91375}, {"source": "202", "target": "206", "value": 8.91375}, {"source": "202", "target": "207", "value": 1.24625}, {"source": "207", "target": "202", "value": 1.24625}, {"source": "208", "target": "204", "value": 2.79125}, {"source": "204", "target": "208", "value": 2.79125}, {"source": "207", "target": "208", "value": 1.29}, {"source": "208", "target": "207", "value": 1.29}, {"source": "209", "target": "208", "value": 2.085}, {"source": "208", "target": "209", "value": 2.085}, {"source": "210", "target": "209", "value": 2.73875}, {"source": "209", "target": "210", "value": 2.73875}, {"source": "211", "target": "210", "value": 0.37875}, {"source": "210", "target": "211", "value": 0.37875}, {"source": "212", "target": "211", "value": 2.89}, {"source": "211", "target": "212", "value": 2.89}, {"source": "213", "target": "212", "value": 1.5975}, {"source": "212", "target": "213", "value": 1.5975}, {"source": "214", "target": "183", "value": 1.45125}, {"source": "183", "target": "214", "value": 1.45125}, {"source": "215", "target": "214", "value": 2.4725}, {"source": "214", "target": "215", "value": 2.4725}, {"source": "216", "target": "215", "value": 1.355}, {"source": "215", "target": "216", "value": 1.355}, {"source": "217", "target": "218", "value": 1.38625}, {"source": "218", "target": "217", "value": 1.38625}, {"source": "216", "target": "219", "value": 4.4925}, {"source": "219", "target": "216", "value": 4.4925}, {"source": "95", "target": "216", "value": 3.195}, {"source": "216", "target": "95", "value": 3.195}, {"source": "97", "target": "95", "value": 1.5425}, {"source": "95", "target": "97", "value": 1.5425}, {"source": "220", "target": "97", "value": 4.30625}, {"source": "97", "target": "220", "value": 4.30625}, {"source": "221", "target": "222", "value": 0.995}, {"source": "222", "target": "221", "value": 0.995}, {"source": "214", "target": "217", "value": 3.85875}, {"source": "217", "target": "214", "value": 3.85875}, {"source": "217", "target": "223", "value": 3.695}, {"source": "223", "target": "217", "value": 3.695}, {"source": "224", "target": "225", "value": 17.8025}, {"source": "225", "target": "224", "value": 17.8025}, {"source": "222", "target": "224", "value": 1.52375}, {"source": "224", "target": "222", "value": 1.52375}, {"source": "224", "target": "226", "value": 0.9525}, {"source": "226", "target": "224", "value": 0.9525}, {"source": "226", "target": "227", "value": 0.62875}, {"source": "227", "target": "226", "value": 0.62875}, {"source": "227", "target": "228", "value": 5.13875}, {"source": "228", "target": "227", "value": 5.13875}, {"source": "220", "target": "230", "value": 4.03625}, {"source": "230", "target": "220", "value": 4.03625}, {"source": "231", "target": "220", "value": 1.5425}, {"source": "220", "target": "231", "value": 1.5425}, {"source": "232", "target": "231", "value": 4.23125}, {"source": "231", "target": "232", "value": 4.23125}, {"source": "233", "target": "99", "value": 0.62875}, {"source": "99", "target": "233", "value": 0.62875}, {"source": "232", "target": "99", "value": 0.34375}, {"source": "99", "target": "232", "value": 0.34375}, {"source": "233", "target": "232", "value": 0.34375}, {"source": "232", "target": "233", "value": 0.34375}, {"source": "234", "target": "233", "value": 0.41625}, {"source": "233", "target": "234", "value": 0.41625}, {"source": "235", "target": "234", "value": 3.1}, {"source": "234", "target": "235", "value": 3.1}, {"source": "231", "target": "221", "value": 4.2725}, {"source": "221", "target": "231", "value": 4.2725}, {"source": "236", "target": "221", "value": 9.7025}, {"source": "221", "target": "236", "value": 9.7025}, {"source": "234", "target": "237", "value": 2.61125}, {"source": "237", "target": "234", "value": 2.61125}, {"source": "238", "target": "235", "value": 0.89125}, {"source": "235", "target": "238", "value": 0.89125}, {"source": "239", "target": "238", "value": 4.845}, {"source": "238", "target": "239", "value": 4.845}, {"source": "238", "target": "240", "value": 1.675}, {"source": "240", "target": "238", "value": 1.675}, {"source": "241", "target": "242", "value": 2.175}, {"source": "242", "target": "241", "value": 2.175}, {"source": "241", "target": "243", "value": 1.97}, {"source": "243", "target": "241", "value": 1.97}, {"source": "244", "target": "239", "value": 0.83375}, {"source": "239", "target": "244", "value": 0.83375}, {"source": "244", "target": "241", "value": 2.0875}, {"source": "241", "target": "244", "value": 2.0875}, {"source": "245", "target": "244", "value": 1.57125}, {"source": "244", "target": "245", "value": 1.57125}, {"source": "235", "target": "236", "value": 6.18}, {"source": "236", "target": "235", "value": 6.18}, {"source": "239", "target": "246", "value": 2.63625}, {"source": "246", "target": "239", "value": 2.63625}, {"source": "245", "target": "247", "value": 3.5975}, {"source": "247", "target": "245", "value": 3.5975}, {"source": "100", "target": "249", "value": 0.3225}, {"source": "249", "target": "100", "value": 0.3225}, {"source": "250", "target": "13", "value": 2.62875}, {"source": "13", "target": "250", "value": 2.62875}, {"source": "251", "target": "250", "value": 7.43625}, {"source": "250", "target": "251", "value": 7.43625}, {"source": "252", "target": "203", "value": 2.11125}, {"source": "203", "target": "252", "value": 2.11125}, {"source": "252", "target": "253", "value": 3.72875}, {"source": "253", "target": "252", "value": 3.72875}, {"source": "13", "target": "236", "value": 4.96375}, {"source": "236", "target": "13", "value": 4.96375}, {"source": "254", "target": "228", "value": 16.27375}, {"source": "228", "target": "254", "value": 16.27375}, {"source": "228", "target": "255", "value": 1.625}, {"source": "255", "target": "228", "value": 1.625}, {"source": "256", "target": "257", "value": 0.69}, {"source": "257", "target": "256", "value": 0.69}, {"source": "255", "target": "256", "value": 4.9775}, {"source": "256", "target": "255", "value": 4.9775}, {"source": "256", "target": "258", "value": 0.9825}, {"source": "258", "target": "256", "value": 0.9825}, {"source": "255", "target": "259", "value": 3.86125}, {"source": "259", "target": "255", "value": 3.86125}, {"source": "100", "target": "260", "value": 3.475}, {"source": "260", "target": "100", "value": 3.475}, {"source": "259", "target": "261", "value": 5.16625}, {"source": "261", "target": "259", "value": 5.16625}, {"source": "262", "target": "252", "value": 4.85}, {"source": "252", "target": "262", "value": 4.85}, {"source": "206", "target": "262", "value": 1.02375}, {"source": "262", "target": "206", "value": 1.02375}, {"source": "263", "target": "206", "value": 1.77125}, {"source": "206", "target": "263", "value": 1.77125}, {"source": "262", "target": "264", "value": 7.0825}, {"source": "264", "target": "262", "value": 7.0825}, {"source": "213", "target": "263", "value": 2.7225}, {"source": "263", "target": "213", "value": 2.7225}, {"source": "265", "target": "213", "value": 1.255}, {"source": "213", "target": "265", "value": 1.255}, {"source": "266", "target": "265", "value": 1.11625}, {"source": "265", "target": "266", "value": 1.11625}, {"source": "267", "target": "266", "value": 3.43375}, {"source": "266", "target": "267", "value": 3.43375}, {"source": "268", "target": "266", "value": 15.98375}, {"source": "266", "target": "268", "value": 15.98375}, {"source": "259", "target": "269", "value": 1.59625}, {"source": "269", "target": "259", "value": 1.59625}, {"source": "270", "target": "271", "value": 2.57375}, {"source": "271", "target": "270", "value": 2.57375}, {"source": "250", "target": "272", "value": 1.4725}, {"source": "272", "target": "250", "value": 1.4725}, {"source": "272", "target": "273", "value": 0.44125}, {"source": "273", "target": "272", "value": 0.44125}, {"source": "273", "target": "274", "value": 2.14875}, {"source": "274", "target": "273", "value": 2.14875}, {"source": "273", "target": "254", "value": 1.1875}, {"source": "254", "target": "273", "value": 1.1875}, {"source": "275", "target": "254", "value": 2.52875}, {"source": "254", "target": "275", "value": 2.52875}, {"source": "275", "target": "276", "value": 1.7825}, {"source": "276", "target": "275", "value": 1.7825}, {"source": "270", "target": "277", "value": 0.95125}, {"source": "277", "target": "270", "value": 0.95125}, {"source": "278", "target": "270", "value": 0.8375}, {"source": "270", "target": "278", "value": 0.8375}, {"source": "279", "target": "278", "value": 2.20375}, {"source": "278", "target": "279", "value": 2.20375}, {"source": "269", "target": "280", "value": 0.5325}, {"source": "280", "target": "269", "value": 0.5325}, {"source": "281", "target": "268", "value": 0.695}, {"source": "268", "target": "281", "value": 0.695}, {"source": "282", "target": "281", "value": 3.7425}, {"source": "281", "target": "282", "value": 3.7425}, {"source": "279", "target": "281", "value": 11.8625}, {"source": "281", "target": "279", "value": 11.8625}, {"source": "283", "target": "282", "value": 1.1275}, {"source": "282", "target": "283", "value": 1.1275}, {"source": "279", "target": "284", "value": 4.36125}, {"source": "284", "target": "279", "value": 4.36125}, {"source": "285", "target": "279", "value": 5.4175}, {"source": "279", "target": "285", "value": 5.4175}, {"source": "286", "target": "287", "value": 2.38875}, {"source": "287", "target": "286", "value": 2.38875}, {"source": "288", "target": "187", "value": 17.05625}, {"source": "187", "target": "288", "value": 17.05625}, {"source": "289", "target": "129", "value": 11.45875}, {"source": "129", "target": "289", "value": 11.45875}, {"source": "290", "target": "289", "value": 8.8725}, {"source": "289", "target": "290", "value": 8.8725}, {"source": "288", "target": "291", "value": 0.565}, {"source": "291", "target": "288", "value": 0.565}, {"source": "292", "target": "288", "value": 0.935}, {"source": "288", "target": "292", "value": 0.935}, {"source": "291", "target": "293", "value": 4.56625}, {"source": "293", "target": "291", "value": 4.56625}, {"source": "292", "target": "291", "value": 0.74625}, {"source": "291", "target": "292", "value": 0.74625}, {"source": "294", "target": "293", "value": 8.05875}, {"source": "293", "target": "294", "value": 8.05875}, {"source": "293", "target": "295", "value": 7.0425}, {"source": "295", "target": "293", "value": 7.0425}, {"source": "293", "target": "296", "value": 3.46625}, {"source": "296", "target": "293", "value": 3.46625}, {"source": "195", "target": "294", "value": 5.1125}, {"source": "294", "target": "195", "value": 5.1125}, {"source": "297", "target": "298", "value": 0.70125}, {"source": "298", "target": "297", "value": 0.70125}, {"source": "209", "target": "297", "value": 4.92125}, {"source": "297", "target": "209", "value": 4.92125}, {"source": "297", "target": "299", "value": 3.13}, {"source": "299", "target": "297", "value": 3.13}, {"source": "295", "target": "298", "value": 2.01875}, {"source": "298", "target": "295", "value": 2.01875}, {"source": "295", "target": "300", "value": 2.5275}, {"source": "300", "target": "295", "value": 2.5275}, {"source": "285", "target": "286", "value": 2.1675}, {"source": "286", "target": "285", "value": 2.1675}, {"source": "173", "target": "177", "value": 5.48875}, {"source": "177", "target": "173", "value": 5.48875}, {"source": "179", "target": "171", "value": 12.795}, {"source": "171", "target": "179", "value": 12.795}, {"source": "185", "target": "197", "value": 9.955}, {"source": "197", "target": "185", "value": 9.955}, {"source": "196", "target": "193", "value": 4.965}, {"source": "193", "target": "196", "value": 4.965}, {"source": "113", "target": "109", "value": 5.01125}, {"source": "109", "target": "113", "value": 5.01125}, {"source": "188", "target": "114", "value": 9.3775}, {"source": "114", "target": "188", "value": 9.3775}, {"source": "191", "target": "189", "value": 0.30125}, {"source": "189", "target": "191", "value": 0.30125}, {"source": "280", "target": "268", "value": 1.33875}, {"source": "268", "target": "280", "value": 1.33875}, {"source": "277", "target": "275", "value": 0.79125}, {"source": "275", "target": "277", "value": 0.79125}, {"source": "277", "target": "271", "value": 3.475}, {"source": "271", "target": "277", "value": 3.475}, {"source": "116", "target": "110", "value": 4.6875}, {"source": "110", "target": "116", "value": 4.6875}, {"source": "230", "target": "260", "value": 1.1225}, {"source": "260", "target": "230", "value": 1.1225}]}